pybrid/__init__.py
pybrid/base/__init__.py
pybrid/base/analog/__init__.py
pybrid/base/analog/computations.c
pybrid/base/analog/computations.cpython-312-x86_64-linux-gnu.so
pybrid/base/hybrid/__init__.py
pybrid/base/hybrid/computer.c
pybrid/base/hybrid/computer.cpython-312-x86_64-linux-gnu.so
pybrid/base/hybrid/controller.c
pybrid/base/hybrid/controller.cpython-312-x86_64-linux-gnu.so
pybrid/base/hybrid/elements.c
pybrid/base/hybrid/elements.cpython-312-x86_64-linux-gnu.so
pybrid/base/hybrid/entities.c
pybrid/base/hybrid/entities.cpython-312-x86_64-linux-gnu.so
pybrid/base/hybrid/exceptions.c
pybrid/base/hybrid/exceptions.cpython-312-x86_64-linux-gnu.so
pybrid/base/hybrid/modules.c
pybrid/base/hybrid/modules.cpython-312-x86_64-linux-gnu.so
pybrid/base/hybrid/protocol.c
pybrid/base/hybrid/protocol.cpython-312-x86_64-linux-gnu.so
pybrid/base/hybrid/run.c
pybrid/base/hybrid/run.cpython-312-x86_64-linux-gnu.so
pybrid/base/hybrid/serializer.c
pybrid/base/hybrid/serializer.cpython-312-x86_64-linux-gnu.so
pybrid/base/hybrid/utils.c
pybrid/base/hybrid/utils.cpython-312-x86_64-linux-gnu.so
pybrid/base/hybrid/programs/__init__.py
pybrid/base/hybrid/programs/base.c
pybrid/base/hybrid/programs/base.cpython-312-x86_64-linux-gnu.so
pybrid/base/hybrid/programs/recl.c
pybrid/base/hybrid/programs/recl.cpython-312-x86_64-linux-gnu.so
pybrid/base/hybrid/programs/state.c
pybrid/base/hybrid/programs/state.cpython-312-x86_64-linux-gnu.so
pybrid/base/proto/__init__.py
pybrid/base/proto/main_pb2.py
pybrid/base/proto/main_pb2.pyi
pybrid/base/transport/__init__.py
pybrid/base/transport/base.c
pybrid/base/transport/base.cpython-312-x86_64-linux-gnu.so
pybrid/base/transport/passthrough.c
pybrid/base/transport/passthrough.cpython-312-x86_64-linux-gnu.so
pybrid/base/transport/serial.c
pybrid/base/transport/serial.cpython-312-x86_64-linux-gnu.so
pybrid/base/transport/stream.c
pybrid/base/transport/stream.cpython-312-x86_64-linux-gnu.so
pybrid_computing-0.11.1.dist-info/METADATA
pybrid_computing-0.11.1.dist-info/WHEEL
pybrid_computing-0.11.1.dist-info/entry_points.txt
pybrid_computing-0.11.1.dist-info/top_level.txt
pybrid_computing-0.11.1.dist-info/RECORD
