Metadata-Version: 2.4
Name: pybrid-computing
Version: 0.11.1
Summary: Library to interact with analog computers and analog-digital hybrid computers, in particular the LUCIDAC and REDAC computers made by anabrid
Home-page: https://anabrid.com/
Author: Michael Steck
Author-email: pybrid-code@anabrid.com
Requires-Python: >=3.11,<4.0
Requires-Dist: anyio>=4.11.0
Requires-Dist: asyncclick>=8.2.2.2
Requires-Dist: inflection>=0.5.1
Requires-Dist: matplotlib>=3.10.6
Requires-Dist: packaging>=25.0
Requires-Dist: protobuf>=6.31.1
Requires-Dist: pydantic>=2.11.9
Requires-Dist: pyftdi>=0.57.1
Requires-Dist: pyi>=0.1.0
Requires-Dist: zeroconf>=0.147.2
Requires-Dist: prompt-toolkit>=3.0.52
Requires-Dist: pyserial-asyncio>=0.6
Dynamic: author
Dynamic: author-email
Dynamic: home-page
Dynamic: requires-python
